AUTHORS
COPYING
COPYING.LESSER
README
TODO
achoo.py
setup.cfg
setup.py
test.py
Achoo.egg-info/PKG-INFO
Achoo.egg-info/SOURCES.txt
Achoo.egg-info/dependency_links.txt
Achoo.egg-info/top_level.txt
setup/__init__.py
setup/epydoc.py
setup/ez_setup.py
setup/pyunit.py