Metadata-Version: 1.0
Name: Achoo
Version: 1.0
Summary: A fluent interface for testing Python objects.
Home-page: http://web.quuxo.com/projects/achoo
Author: Quuxo Software
Author-email: contact@quuxo.com
License: UNKNOWN
Platform: UNKNOWN
